{
  "schema_version": "1.0",
  "model_version": "ai-model-version-placeholder",
  "prompt_version": "complaint-extraction-v1",
  "language": "pl",
  "language_confidence": 0.97,
  "order_id": "ORD-2026-00421",
  "customer_name": "AutoParts Example Sp. z o.o.",
  "customer_identifier": {
    "email": "quality@example-customer.test",
    "external_id": null,
    "confidence": 0.91
  },
  "defect_description": "Klient zgłasza pęknięcie metalowego uchwytu po montażu. Do wiadomości dołączono zdjęcia defektu.",
  "suggested_category": "pęknięcie komponentu",
  "confidence": 0.86,
  "requires_human_review": true,
  "human_review_reasons": [
    "missing_batch_number"
  ],
  "missing_information": [
    "batch_id"
  ],
  "summary": "Reklamacja dotyczy pęknięcia metalowego komponentu z zamówienia ORD-2026-00421. Brakuje numeru partii.",
  "safety_notes": [
    "AI nie potwierdza zasadności reklamacji.",
    "Draft odpowiedzi nie powinien obiecywać uznania reklamacji przed walidacją jakościową."
  ],
  "validation_warnings": [
    "Numer partii nie został znaleziony w treści emaila.",
    "Wymagana walidacja order_id w SAP."
  ],
  "response_draft": "Dziękujemy za zgłoszenie reklamacji. Przyjęliśmy sprawę dotyczącą zamówienia ORD-2026-00421. Prosimy o dosłanie numeru partii, jeśli jest dostępny na etykiecie lub dokumentacji dostawy.",
  "image_hints": [
    {
      "file_name": "defect-photo-1.jpg",
      "hint": "Widoczne uszkodzenie może odpowiadać pęknięciu lub złamaniu elementu.",
      "confidence": 0.72,
      "requires_human_review": true
    }
  ]
}
